README.md
setup.cfg
setup.py
django_grpc_bus/__init__.py
django_grpc_bus/apps.py
django_grpc_bus/exceptions.py
django_grpc_bus/generics.py
django_grpc_bus/handlers.py
django_grpc_bus/mixins.py
django_grpc_bus/serializers.py
django_grpc_bus/server.py
django_grpc_bus/services.py
django_grpc_bus/settings.py
django_grpc_bus.egg-info/PKG-INFO
django_grpc_bus.egg-info/SOURCES.txt
django_grpc_bus.egg-info/dependency_links.txt
django_grpc_bus.egg-info/not-zip-safe
django_grpc_bus.egg-info/requires.txt
django_grpc_bus.egg-info/top_level.txt
django_grpc_bus/client/__init__.py
django_grpc_bus/client/client.py
django_grpc_bus/client/registry.py
django_grpc_bus/management/__init__.py
django_grpc_bus/management/commands/__init__.py
django_grpc_bus/management/commands/generategrpc.py
django_grpc_bus/management/commands/generatemetayaml.py
django_grpc_bus/management/commands/generateproto.py
django_grpc_bus/management/commands/generateservices.py
django_grpc_bus/management/commands/rungrpcserver.py
django_grpc_bus/protobuf/__init__.py
django_grpc_bus/protobuf/generators.py
django_grpc_bus/protobuf/json_format.py
django_grpc_bus/utils/__init__.py
django_grpc_bus/utils/generators.py
django_grpc_bus/utils/model_meta.py
django_grpc_bus/utils/service_meta.py