Metadata-Version: 2.1
Name: django-grpc-bus
Version: 1.0.2
Summary: Django rest gRPC framework
Home-page: https://github.com/rameezarshad/django-grpc-framework
Author: Rameez Arshad
Author-email: rameez.arshad@outlook.in
License: UNKNOWN
Download-URL: https://github.com/rameezarshad/django-grpc-framework/archive/main.zip
Keywords: grpc framework django rest micro service message bus
Platform: UNKNOWN
Classifier: Development Status :: 4 - Beta
Classifier: Intended Audience :: Developers
Classifier: License :: OSI Approved :: Apache Software License
Classifier: Programming Language :: Python :: 3
Classifier: Programming Language :: Python :: 3.6
Classifier: Programming Language :: Python :: 3.7
Classifier: Programming Language :: Python :: 3.8
Requires-Python: >=3.6
